shapeslib/__init__.py
shapeslib/shape.py
shapeslib-0.0.1.dist-info/METADATA
shapeslib-0.0.1.dist-info/WHEEL
shapeslib-0.0.1.dist-info/top_level.txt
shapeslib-0.0.1.dist-info/RECORD
