Metadata-Version: 2.4
Name: shapeslib
Version: 0.0.1
Summary: Библиотека для вычисления площадей фигур
Home-page: https://github.com/vladislav032/testTaskMindbox1
Author: vlad
Author-email: velikiy6789@gmail.com
Project-URL: GitHub, https://github.com/vladislav032/testTaskMindbox1
Classifier: Programming Language :: Python :: 3.11
Classifier: Operating System :: OS Independent
Requires-Python: >=3.6
Requires-Dist: requests>=2.25.1
Dynamic: author
Dynamic: author-email
Dynamic: classifier
Dynamic: description
Dynamic: description-content-type
Dynamic: home-page
Dynamic: project-url
Dynamic: requires-dist
Dynamic: requires-python
Dynamic: summary
